mortal_sqlparse/__init__.py
mortal_sqlparse/sqlparse_main.pyd
mortal_sqlparse/sqlparse_main.so
mortal_sqlparse-2.3.19.dist-info/METADATA
mortal_sqlparse-2.3.19.dist-info/WHEEL
mortal_sqlparse-2.3.19.dist-info/top_level.txt
mortal_sqlparse-2.3.19.dist-info/RECORD
