Metadata-Version: 2.1
Name: mortal-sqlparse
Version: 2.3.19
Summary: 'mortal工具集::sqlparse'
Author: MJ
Requires-Python: <=3.11,>=3.10
Requires-Dist: mortal-timer
Requires-Dist: mortal-var
Requires-Dist: moz-sql-parser
